abotserver/__init__.py
abotserver/cmd.py
abotserver/logging.py
abotserver/main.py
abotserver/process.py
abotserver/providers/__init__.py
abotserver/providers/aliyun.py
abotserver/providers/hikvision.py
abotserver/providers/jsst.py
abotserver/routers/__init__.py
abotserver/routers/aliyun.py
abotserver/routers/hikvision.py
abotserver/routers/index.py
abotserver/routers/jsst.py
abotserver-2022rc3.dist-info/entry_points.txt
abotserver-2022rc3.dist-info/WHEEL
abotserver-2022rc3.dist-info/METADATA
abotserver-2022rc3.dist-info/RECORD
