Metadata-Version: 2.1
Name: abotserver
Version: 2022rc3
Summary: 
Author: fineartit
Author-email: fineartit@outlook.com
Requires-Python: >=3.7,<4.0
Classifier: Programming Language :: Python :: 3
Classifier: Programming Language :: Python :: 3.10
Classifier: Programming Language :: Python :: 3.7
Classifier: Programming Language :: Python :: 3.8
Classifier: Programming Language :: Python :: 3.9
Requires-Dist: aliyun-python-sdk-core (>=2.13.36,<3.0.0)
Requires-Dist: aliyun-python-sdk-nlp-automl (>=0.0.9,<0.0.10)
Requires-Dist: fastapi (>=0.79.0,<0.80.0)
Requires-Dist: gunicorn (>=20.1.0,<21.0.0)
Requires-Dist: lockfile (>=0.12.2,<0.13.0)
Requires-Dist: psutil (>=5.9.1,<6.0.0)
Requires-Dist: python-daemon (>=2.3.0,<3.0.0)
Requires-Dist: requests (>=2.28.1,<3.0.0)
Requires-Dist: uvicorn (>=0.18.2,<0.19.0)
